README.rst
setup.py
tests/__init__.py
tests/fake_server.py
tests/test_batch_tar.py
tests/test_cant_deploy_python3.py
tests/test_requirements.py
tests/test_split_test.py
tests/test_submodules.py
tests/test_yhat_json.py
yhat/__init__.py
yhat/api.py
yhat/batch.py
yhat/credentials.py
yhat/requirements.py
yhat/submodules.py
yhat/utils.py
yhat/version.py
yhat/yhat_json.py
yhat.egg-info/PKG-INFO
yhat.egg-info/SOURCES.txt
yhat.egg-info/dependency_links.txt
yhat.egg-info/requires.txt
yhat.egg-info/top_level.txt
yhat/deployment/__init__.py
yhat/deployment/input_and_output.py
yhat/deployment/models.py
yhat/deployment/reindenter.py
yhat/deployment/save_session.py