Metadata-Version: 1.0
Name: yhat
Version: 1.10.0
Summary: Python client for Yhat (http://yhat.com/)
Home-page: https://github.com/yhat/yhat-client
Author: Greg Lamp
Author-email: greg@yhathq.com
License: BSD
Keywords: yhat,scikits,numpy,pandas
Platform: UNKNOWN
